CHANGES.txt
LICENSE.txt
MANIFEST.in
README.txt
setup.py
src/j01/__init__.py
src/j01.wizard.egg-info/PKG-INFO
src/j01.wizard.egg-info/SOURCES.txt
src/j01.wizard.egg-info/dependency_links.txt
src/j01.wizard.egg-info/namespace_packages.txt
src/j01.wizard.egg-info/not-zip-safe
src/j01.wizard.egg-info/requires.txt
src/j01.wizard.egg-info/top_level.txt
src/j01/wizard/__init__.py
src/j01/wizard/browser.zcml
src/j01/wizard/btn.py
src/j01/wizard/checker.txt
src/j01/wizard/configure.zcml
src/j01/wizard/interfaces.py
src/j01/wizard/menu.pt
src/j01/wizard/step.pt
src/j01/wizard/step.py
src/j01/wizard/tests.py
src/j01/wizard/wizard.py